corpkit/__init__.py
corpkit/annotate.py
corpkit/build.py
corpkit/completer.py
corpkit/configurations.py
corpkit/conll.py
corpkit/constants.py
corpkit/convert.py
corpkit/corpkit
corpkit/corpkit.1
corpkit/corpus.py
corpkit/cql.py
corpkit/env.py
corpkit/hdf5.py
corpkit/inflect.py
corpkit/interrogation.py
corpkit/interrogator.py
corpkit/jsons.py
corpkit/keys.py
corpkit/layouts.py
corpkit/lazyprop.py
corpkit/matches.py
corpkit/model.py
corpkit/multiprocess.py
corpkit/new_project
corpkit/noseinstall.py
corpkit/nosetests.py
corpkit/other.py
corpkit/parse.py
corpkit/plotter.py
corpkit/plugins.py
corpkit/process.py
corpkit/query.py
corpkit/stats.py
corpkit/tiger.py
corpkit/tokenise.py
corpkit/views.py
corpkit/wrapper.py
corpkit/dictionaries/__init__.py
corpkit/dictionaries/bnc.p
corpkit/dictionaries/bnc.py
corpkit/dictionaries/eng_verb_lexicon.p
corpkit/dictionaries/process_types.py
corpkit/dictionaries/queries.py
corpkit/dictionaries/roles.py
corpkit/dictionaries/stopwords.py
corpkit/dictionaries/verblist.py
corpkit/dictionaries/word_transforms.py
corpkit/dictionaries/wordlists.py
corpkit/download/__init__.py
corpkit/download/corenlp.py
corpkit/langprops/arabic.properties
corpkit/langprops/chinese.properties
corpkit/langprops/french.properties
corpkit/langprops/german.properties
corpkit/langprops/spanish.properties
pollux/__init__.py
pollux/config.py
pollux/start.py
pollux/scripts/pollux
pollux/scripts/pollux-add
pollux/scripts/pollux-build
pollux/scripts/pollux-install-corenlp
pollux/scripts/pollux-parse
pollux/scripts/pollux-quickstart
pollux/static/Info.plist
pollux/static/bootstrap-toggle.min.css
pollux/static/favicon.icns
pollux/static/favicon.ico
pollux/static/oInfo.plist
pollux/static/old-favicon.icns
pollux/static/style.css
pollux/static/templates.html
pollux/static/toucan-head.png
pollux/static/toucan-small.png
pollux/static/bootstrap-table/bootstrap-table-locale-all.js
pollux-1.0.4.dist-info/DESCRIPTION.rst
pollux-1.0.4.dist-info/METADATA
pollux-1.0.4.dist-info/RECORD
pollux-1.0.4.dist-info/WHEEL
pollux-1.0.4.dist-info/dependency_links.txt
pollux-1.0.4.dist-info/metadata.json
pollux-1.0.4.dist-info/top_level.txt
