Metadata-Version: 2.0
Name: pollux
Version: 1.0.4
Summary: Sophisticated corpus linguistics
Home-page: http://github.com/interrogator/pollux
Author: Daniel McDonald
Author-email: mcddjx@gmail.com
License: MIT
Keywords: corpus,linguistics,nlp
Platform: UNKNOWN
Requires-Dist: blessings (>=1.6)
Requires-Dist: chardet
Requires-Dist: joblib
Requires-Dist: nltk (>=3.0.0)
Requires-Dist: numpy (>=1.12.0)
Requires-Dist: pandas (>=0.19.2)
Requires-Dist: requests
Requires-Dist: tabview (>=1.4.0)
Requires-Dist: tqdm (>=4.11.2)
Requires-Dist: traitlets (>=4.1.0)
Provides-Extra: all
Requires-Dist: Flask (>=0.12.1); extra == 'all'
Requires-Dist: blessings (>=1.6); extra == 'all'
Requires-Dist: cx-Freeze; extra == 'all'
Requires-Dist: flask-Bootstrap (>=3.3.7.1); extra == 'all'
Requires-Dist: flask-WTF; extra == 'all'
Requires-Dist: matplotlib (>=1.4.3); extra == 'all'
Requires-Dist: pyobjc; extra == 'all'
Requires-Dist: rumps; extra == 'all'
Requires-Dist: tables; extra == 'all'
Requires-Dist: tabview (>=1.4.0); extra == 'all'
Provides-Extra: app
Requires-Dist: Flask (>=0.12.1); extra == 'app'
Requires-Dist: flask-Bootstrap (>=3.3.7.1); extra == 'app'
Requires-Dist: flask-WTF; extra == 'app'
Requires-Dist: pyobjc; extra == 'app'
Requires-Dist: rumps; extra == 'app'
Provides-Extra: dev
Requires-Dist: Flask (>=0.12.1); extra == 'dev'
Requires-Dist: blessings (>=1.6); extra == 'dev'
Requires-Dist: cx-Freeze; extra == 'dev'
Requires-Dist: flask-Bootstrap (>=3.3.7.1); extra == 'dev'
Requires-Dist: flask-WTF; extra == 'dev'
Requires-Dist: matplotlib (>=1.4.3); extra == 'dev'
Requires-Dist: pyobjc; extra == 'dev'
Requires-Dist: rumps; extra == 'dev'
Requires-Dist: tables; extra == 'dev'
Requires-Dist: tabview (>=1.4.0); extra == 'dev'
Provides-Extra: env
Requires-Dist: blessings (>=1.6); extra == 'env'
Requires-Dist: matplotlib (>=1.4.3); extra == 'env'
Requires-Dist: tables; extra == 'env'
Requires-Dist: tabview (>=1.4.0); extra == 'env'
Provides-Extra: mac_app
Requires-Dist: Flask (>=0.12.1); extra == 'mac_app'
Requires-Dist: flask-Bootstrap (>=3.3.7.1); extra == 'mac_app'
Requires-Dist: flask-WTF; extra == 'mac_app'
